{"chunkName":"components/w-button","global":true,"kebabName":"w-button","pascalName":"WButton","prefetch":false,"preload":false,"mode":"all","priority":0,"meta":{"type":1,"props":[{"name":"disabled","global":false,"description":"","tags":[],"required":false,"type":"boolean | undefined","schema":{"kind":"enum","type":"boolean | undefined","schema":{"0":"undefined","1":"false","2":"true"}}},{"name":"readonly","global":false,"description":"","tags":[],"required":false,"type":"boolean | undefined","schema":{"kind":"enum","type":"boolean | undefined","schema":{"0":"undefined","1":"false","2":"true"}}},{"name":"border","global":false,"default":"true","description":"","tags":[],"required":false,"type":"boolean | undefined","schema":{"kind":"enum","type":"boolean | undefined","schema":{"0":"undefined","1":"false","2":"true"}}},{"name":"unstyle","global":false,"description":"","tags":[],"required":false,"type":"boolean | undefined","schema":{"kind":"enum","type":"boolean | undefined","schema":{"0":"undefined","1":"false","2":"true"}}},{"name":"label","global":false,"default":"\"\"","description":"","tags":[],"required":false,"type":"string | undefined","schema":{"kind":"enum","type":"string | undefined","schema":{"0":"undefined","1":"string"}}},{"name":"color","global":false,"default":"false","description":"","tags":[],"required":false,"type":"string | boolean | undefined","schema":{"kind":"enum","type":"string | boolean | undefined","schema":{"0":"undefined","1":"string","2":"false","3":"true"}}}],"slots":[{"name":"label","type":"{ classes: string; }","description":"","tags":[],"schema":{"kind":"object","type":"{ classes: string; }","schema":{"classes":{"name":"classes","global":false,"description":"","tags":[],"required":true,"type":"string","schema":"string"}}}},{"name":"icon","type":"{}","description":"","tags":[],"schema":{"kind":"object","type":"{}","schema":{}}},{"name":"default","type":"{ label: string; }","description":"","tags":[],"schema":{"kind":"object","type":"{ label: string; }","schema":{"label":{"name":"label","global":false,"description":"","tags":[],"required":true,"type":"string","schema":"string"}}}},{"name":"icon-after","type":"{}","description":"","tags":[],"schema":{"kind":"object","type":"{}","schema":{}}}],"events":[],"exposed":[],"hash":"XRCLqcHxdT4hegfv_7RAk61e-iqBLHm_GnZMgCaLlfs"},"filePath":"../dist/runtime/components/WButton/WButton.vue","name":"WButton"}